README.md
setup.py
circle_douya.egg-info/PKG-INFO
circle_douya.egg-info/SOURCES.txt
circle_douya.egg-info/dependency_links.txt
circle_douya.egg-info/entry_points.txt
circle_douya.egg-info/top_level.txt
get_circle/__init__.py