Metadata-Version: 1.0
Name: circle-douya
Version: 0.0.1
Summary: 画圆
Home-page: https://github.com/qumeili/circle_douya
Author: douya
Author-email: 1664619362@qq.com
License: UNKNOWN
Platform: UNKNOWN
